{
  "schemaVersion": 1,
  "featureId": "feat_route_e6ae1b34db",
  "title": "Django route /financeswallet/add/",
  "summary": "Django route /financeswallet/add/ handled by WalletAddView.as_view in Finances/urls.py.",
  "kind": "route",
  "source": "python-django-route",
  "confidence": "high",
  "entrypoints": [
    {
      "path": "Finances/urls.py",
      "symbol": "WalletAddView.as_view",
      "route": "/financeswallet/add/",
      "command": null
    }
  ],
  "ownedFiles": [
    {
      "path": "Finances/urls.py",
      "reason": "Django URL route declaration"
    }
  ],
  "contextFiles": [],
  "tests": [],
  "tags": [
    "python",
    "django",
    "route"
  ],
  "trustBoundaries": [
    "network",
    "user-input",
    "serialization"
  ],
  "status": "pending",
  "lock": null,
  "findingIds": [],
  "patchAttemptIds": [],
  "analysisHistory": [],
  "createdAt": "2026-05-22T16:02:10.019Z",
  "updatedAt": "2026-05-22T16:02:10.019Z"
}
